UltimatePkg/Mycolor.py
UltimatePkg2-0.4.dist-info/DESCRIPTION.rst
UltimatePkg2-0.4.dist-info/METADATA
UltimatePkg2-0.4.dist-info/RECORD
UltimatePkg2-0.4.dist-info/WHEEL
UltimatePkg2-0.4.dist-info/entry_points.txt
UltimatePkg2-0.4.dist-info/metadata.json
UltimatePkg2-0.4.dist-info/top_level.txt
