Metadata-Version: 2.0
Name: UltimatePkg2
Version: 0.4
Summary: Ultimate packages
Home-page: UNKNOWN
Author: crea
Author-email: masataka0504@gmail.com
License: MIT
Keywords: utilities
Platform: UNKNOWN
Classifier: Programming Language :: Python :: 3.6
Requires-Dist: termcolor
